[
    {
        "name": "Pisspage",
        "color": "violet",
        "points": 1
    },
    {
        "name": "Coiffeur",
        "color": "violet",
        "points": 1
    },
    {
        "name": "Königlicher Kartograf",
        "color": "violet",
        "points": 1
    },
    {
        "name": "Hofdame",
        "color": "violet",
        "points": 1,
        "action": "draw1ActionCard",
        "actionText": "Nachdem du diese Adlige geköpft hast, erhältst du eine zusätzliche Aktionskarte vom Zugstapel.",
        "strategy": "afterBehead"
    },
    {
        "name": "Lord",
        "color": "violet",
        "points": 2,
        "action": "draw1ActionCard",
        "actionText": "Nachdem du diesen Adligen geköpft hast, erhältst du eine zusätzliche Aktionskarte vom Zugstapel.",
        "strategy": "afterBehead"
    },
    {
        "name": "Lady",
        "color": "violet",
        "points": 2,
        "action": "draw1ActionCard",
        "actionText": "Nachdem du diese Adlige geköpft hast, erhältst du eine zusätzliche Aktionskarte vom Zugstapel.",
        "strategy": "afterBehead"
    },
    {
        "name": "Graf",
        "color": "violet",
        "points": 2,
        "action": "addPointsForCountAndCountess",
        "actionText": "Der Graf ist 4 Punkte wert, wenn du auch die Gräfin in deinem Stapel hast.",
        "strategy": "direct"
    },
    {
        "name": "Gräfin",
        "color": "violet",
        "points": 2,
        "action": "addPointsForCountAndCountess",
        "actionText": "Die Gräfin ist 4 Punkte wert, wenn du auch den Graf in deinem Stapel hast.",
        "strategy": "direct"
    },
    {
        "name": "Flotter Fürst",
        "color": "violet",
        "points": 2,
        "action": "behead1",
        "actionText": "Nachdem du diesen Adligen geköpft hast, köpfst du an der Spitze einen weiteren Adligen.",
        "strategy": "afterBehead"
    },
    {
        "name": "Herzog",
        "color": "violet",
        "points": 3
    },
    {
        "name": "Baron",
        "color": "violet",
        "points": 3
    },
    {
        "name": "Robespierre",
        "color": "violet",
        "points": 3,
        "action": "endDay",
        "actionText": "Nachdem du diesen Adligen geköpft hast, endet der Tag. Alle Karten in der Reihe werden auf den Ablagestapel gelegt.",
        "strategy": "afterBehead"
    },
    {
        "name": "Regent",
        "color": "violet",
        "points": 4
    },
    {
        "name": "Marie Antoinette",
        "color": "violet",
        "points": 5
    },
    {
        "name": "König Ludwig XVI.",
        "color": "violet",
        "points": 5
    },
    {
        "name": "Palastwache 1",
        "color": "red",
        "points": 0,
        "action": "addPointsForGuards",
        "actionText": "Der Wert der Palastwache entspricht der Anzahl der Palastwachen in deinem Stapel.",
        "strategy": "direct"
    },
    {
        "name": "Palastwache 2",
        "color": "red",
        "points": 0,
        "action": "addPointsForGuards",
        "actionText": "Der Wert der Palastwache entspricht der Anzahl der Palastwachen in deinem Stapel.",
        "strategy": "direct"
    },
    {
        "name": "Palastwache 3",
        "color": "red",
        "points": 0,
        "action": "addPointsForGuards",
        "actionText": "Der Wert der Palastwache entspricht der Anzahl der Palastwachen in deinem Stapel.",
        "strategy": "direct"
    },
    {
        "name": "Palastwache 4",
        "color": "red",
        "points": 0,
        "action": "addPointsForGuards",
        "actionText": "Der Wert der Palastwache entspricht der Anzahl der Palastwachen in deinem Stapel.",
        "strategy": "direct"
    },
    {
        "name": "Palastwache 5",
        "color": "red",
        "points": 0,
        "action": "addPointsForGuards",
        "actionText": "Der Wert der Palastwache entspricht der Anzahl der Palastwachen in deinem Stapel.",
        "strategy": "direct"
    },
    {
        "name": "Leutnant",
        "color": "red",
        "points": 2
    },
    {
        "name": "Leutnant",
        "color": "red",
        "points": 2
    },
    {
        "name": "Hauptmann der Wache",
        "color": "red",
        "points": 2,
        "action": "add1ToQueue",
        "actionText": "Nachdem du diesen Adligen geköpft hast, lege einen Adligen vom Adelsstapel ans Ende der Reihe.",
        "strategy": "afterBehead"
    },
    {
        "name": "Oberst",
        "color": "red",
        "points": 3
    },
    {
        "name": "General",
        "color": "red",
        "points": 4,
        "action": "add1ToQueue",
        "actionText": "Nachdem du diesen Adligen geköpft hast, lege einen Adligen vom Adelsstapel ans Ende der Reihe.",
        "strategy": "afterBehead"
    },
    {
        "name": "Meisterspion",
        "color": "red",
        "points": 4,
        "action": "moveSelfToEndOfQueue",
        "actionText": "Immer wenn eine Aktionskarte gespielt wurde, wird dieser Adlige ans Ende der Reihe bewegt.",
        "strategy": "afterPlayedActionCard"
    },
    {
        "name": "Tragische Figur",
        "color": "black",
        "points": 0,
        "action": "addPointsForTragicNoble",
        "actionText": "Dieser Adlige ist einen Minuspunkt wert für jeden schwarzen Adligen in deinem Stapel.",
        "strategy": "direct"
    },
    {
        "name": "Unschuldiges Opfer",
        "color": "black",
        "points": -1,
        "interaction": "selectOwnHandActionCard",
        "interactionText": "Wähle eine Aktionskarte aus deiner Hand, die du entfernen möchtest.",
        "action": "removeOwnHandActionCard",
        "actionText": "Nachdem du diesen Adligen geköpft hast, musst du eine deiner Aktionskarten ablegen.",
        "strategy": "afterBehead"
    },
    {
        "name": "Märtyrerin",
        "color": "black",
        "points": -1
    },
    {
        "name": "Märtyrerin",
        "color": "black",
        "points": -1
    },
    {
        "name": "Märtyrerin",
        "color": "black",
        "points": -1
    },
    {
        "name": "Der Clown",
        "color": "black",
        "points": -2
    },
    {
        "name": "Volksheld",
        "color": "black",
        "points": -3
    },
    {
        "name": "Henkersknecht",
        "color": "green",
        "points": 1,
        "action": "draw1FromNobleStack",
        "actionText": "Nachdem du diesen Adligen geköpft hast, erhältst du zusätzlich die oberste Karte vom Adelsstapel.",
        "strategy": "afterBehead"
    },
    {
        "name": "Gendarm",
        "color": "green",
        "points": 1
    },
    {
        "name": "Gendarm",
        "color": "green",
        "points": 1
    },
    {
        "name": "Unbeliebter Richter",
        "color": "green",
        "points": 2,
        "action": "blockActionCards",
        "actionText": "Kein Spieler darf eine Aktionskarte spielen, solange dieser Adlige an der Spitze der Reihe ist.",
        "strategy": "direct"
    },
    {
        "name": "Unbeliebter Richter",
        "color": "green",
        "points": 2,
        "action": "blockActionCards",
        "actionText": "Kein Spieler darf eine Aktionskarte spielen, solange dieser Adlige an der Spitze der Reihe ist.",
        "strategy": "direct"
    },
    {
        "name": "Grundbesitzer",
        "color": "green",
        "points": 2
    },
    {
        "name": "Steuereintreiber",
        "color": "green",
        "points": 2
    },
    {
        "name": "Ratsmitglied",
        "color": "green",
        "points": 3
    },
    {
        "name": "Bürgermeister",
        "color": "green",
        "points": 3
    },
    {
        "name": "Gouverneur",
        "color": "green",
        "points": 4
    },
    {
        "name": "Reicher Priester",
        "color": "blue",
        "points": 1
    },
    {
        "name": "Reicher Priester",
        "color": "blue",
        "points": 1
    },
    {
        "name": "Ketzer",
        "color": "blue",
        "points": 2
    },
    {
        "name": "Bischof",
        "color": "blue",
        "points": 2
    },
    {
        "name": "Böse Nonne",
        "color": "blue",
        "points": 3
    },
    {
        "name": "Erzbischof",
        "color": "blue",
        "points": 4
    },
    {
        "name": "Kardinal",
        "color": "blue",
        "points": 5
    }
]
